metroid/__init__.py
metroid/admin.py
metroid/apps.py
metroid/celery.py
metroid/config.py
metroid/management/__init__.py
metroid/management/commands/__init__.py
metroid/management/commands/metroid.py
metroid/migrations/0001_initial.py
metroid/migrations/0002_failedpublishmessage.py
metroid/migrations/__init__.py
metroid/models.py
metroid/publish.py
metroid/py.typed
metroid/republish.py
metroid/rq.py
metroid/subscribe.py
metroid/typing.py
metroid/utils.py
metroid-1.4.0.dist-info/LICENSE
metroid-1.4.0.dist-info/METADATA
metroid-1.4.0.dist-info/WHEEL
metroid-1.4.0.dist-info/RECORD
