Metadata-Version: 2.1
Name: metroid
Version: 1.4.0
Summary: Metroid - Metro for Django
Home-page: https://github.com/intility/metroid
Keywords: async,django,servicebus,task,celery,worker,rq
Author: Jonas Krüger Svensson
Author-email: jonas.svensson@intility.no
Maintainer: Ali Arfan
Maintainer-email: ali.arfan@intility.no
Requires-Python: >=3.10,<4.0
Classifier: Development Status :: 5 - Production/Stable
Classifier: Environment :: Web Environment
Classifier: Framework :: Django
Classifier: Framework :: Django :: 4.2
Classifier: Framework :: Django :: 5.0
Classifier: Intended Audience :: Developers
Classifier: License :: OSI Approved :: BSD License
Classifier: Operating System :: OS Independent
Classifier: Programming Language :: Python
Classifier: Programming Language :: Python :: 3
Classifier: Programming Language :: Python :: 3.10
Classifier: Programming Language :: Python :: 3.11
Classifier: Programming Language :: Python :: 3.12
Classifier: Topic :: Software Development
Classifier: Topic :: Software Development :: Libraries
Classifier: Topic :: Software Development :: Libraries :: Application Frameworks
Classifier: Topic :: Software Development :: Libraries :: Python Modules
Requires-Dist: Django (>=4.0,<6.0)
Requires-Dist: aiohttp (>=3.8.4,<4.0.0)
Requires-Dist: azure-servicebus (>=7.10.0,<8.0.0)
Requires-Dist: django-guid (>=3.2.0,<4.0.0)
Project-URL: Documentation, https://github.com/intility/metroid
Project-URL: Repository, https://github.com/intility/metroid
